har2py/__init__.py
har2py/main.py
har2py/requests.jinja2
har2py-0.1.2.dist-info/entry_points.txt
har2py-0.1.2.dist-info/LICENSE
har2py-0.1.2.dist-info/WHEEL
har2py-0.1.2.dist-info/METADATA
har2py-0.1.2.dist-info/RECORD
